terverlib/__init__.py
terverlib/task1.py
terverlib/task2.py
terverlib/task3.py
terverlib/task4.py
terverlib/task5.py
terverlib/task6.py
terver_mishker-0.0.4.dist-info/METADATA
terver_mishker-0.0.4.dist-info/WHEEL
terver_mishker-0.0.4.dist-info/top_level.txt
terver_mishker-0.0.4.dist-info/RECORD
