Metadata-Version: 2.4
Name: terver-mishker
Version: 0.0.4
Summary: библиотека для тервера.
Dynamic: description
Dynamic: summary
